akamai_purge_cache/__init__.py
akamai_purge_cache/purge.py
akamai_purge_cache-2.0.1.dist-info/METADATA
akamai_purge_cache-2.0.1.dist-info/WHEEL
akamai_purge_cache-2.0.1.dist-info/entry_points.txt
akamai_purge_cache-2.0.1.dist-info/RECORD
